reciprocal/__init__.py
reciprocal/config.py
reciprocal/menus.py
reciprocal/py.typed
reciprocal/utils.py
reciprocal-0.2.0.dist-info/LICENSE
reciprocal-0.2.0.dist-info/METADATA
reciprocal-0.2.0.dist-info/WHEEL
reciprocal-0.2.0.dist-info/top_level.txt
reciprocal-0.2.0.dist-info/RECORD
