Metadata-Version: 2.1
Name: reciprocal
Version: 0.2.0
Summary: A library for building simple interactive console menus for UNIX based systems
Home-page: https://github.com/matias-santurio/reciprocal
Author: Matías Santurio
Author-email: matiassantuu@gmail.com
Requires-Python: >=3.13
License-File: LICENSE
Requires-Dist: click >=8.0.0
